setup.py
rawa_dist_distributions/Binomialdistribution.py
rawa_dist_distributions/Gaussiandistribution.py
rawa_dist_distributions/Generaldistribution.py
rawa_dist_distributions/__init__.py
rawa_dist_distributions.egg-info/PKG-INFO
rawa_dist_distributions.egg-info/SOURCES.txt
rawa_dist_distributions.egg-info/dependency_links.txt
rawa_dist_distributions.egg-info/not-zip-safe
rawa_dist_distributions.egg-info/top_level.txt